_runtime.abi3.so
bonito_cuda_runtime.libs/libcudart-80664282.so.10.2.89
bonito_cuda_runtime.libs/runtime-6278d10f.so
bonito_cuda_runtime-0.0.2a2.dist-info/top_level.txt
bonito_cuda_runtime-0.0.2a2.dist-info/WHEEL
bonito_cuda_runtime-0.0.2a2.dist-info/RECORD
bonito_cuda_runtime-0.0.2a2.dist-info/METADATA
bonito_cuda_runtime/__init__.py
bonito_cuda_runtime/lib.py
bonito_cuda_runtime/build.py
bonito_cuda_runtime/nn.py
