Metadata-Version: 2.1
Name: bonito-cuda-runtime
Version: 0.0.2a2
Summary: UNKNOWN
Home-page: UNKNOWN
Author: UNKNOWN
Author-email: UNKNOWN
License: UNKNOWN
Platform: UNKNOWN
Requires-Dist: cffi
